CHANGES.txt
LICENSE.txt
MANIFEST.in
README.txt
setup.py
js/__init__.py
js.momentjs.egg-info/PKG-INFO
js.momentjs.egg-info/SOURCES.txt
js.momentjs.egg-info/dependency_links.txt
js.momentjs.egg-info/entry_points.txt
js.momentjs.egg-info/namespace_packages.txt
js.momentjs.egg-info/not-zip-safe
js.momentjs.egg-info/requires.txt
js.momentjs.egg-info/top_level.txt
js/momentjs/__init__.py
js/momentjs/test_moment.js.txt
js/momentjs/resources/moment-timezone-with-data-2010-2020.js
js/momentjs/resources/moment-timezone-with-data-2010-2020.min.js
js/momentjs/resources/moment-timezone-with-data.js
js/momentjs/resources/moment-timezone-with-data.min.js
js/momentjs/resources/moment-timezone.js
js/momentjs/resources/moment-timezone.min.js
js/momentjs/resources/moment-with-locales.js
js/momentjs/resources/moment-with-locales.min.js
js/momentjs/resources/moment.js
js/momentjs/resources/moment.min.js
js/momentjs/resources/locale/af.js
js/momentjs/resources/locale/ar-ma.js
js/momentjs/resources/locale/ar-sa.js
js/momentjs/resources/locale/ar-tn.js
js/momentjs/resources/locale/ar.js
js/momentjs/resources/locale/az.js
js/momentjs/resources/locale/be.js
js/momentjs/resources/locale/bg.js
js/momentjs/resources/locale/bn.js
js/momentjs/resources/locale/bo.js
js/momentjs/resources/locale/br.js
js/momentjs/resources/locale/bs.js
js/momentjs/resources/locale/ca.js
js/momentjs/resources/locale/cs.js
js/momentjs/resources/locale/cv.js
js/momentjs/resources/locale/cy.js
js/momentjs/resources/locale/da.js
js/momentjs/resources/locale/de-at.js
js/momentjs/resources/locale/de.js
js/momentjs/resources/locale/dv.js
js/momentjs/resources/locale/el.js
js/momentjs/resources/locale/en-au.js
js/momentjs/resources/locale/en-ca.js
js/momentjs/resources/locale/en-gb.js
js/momentjs/resources/locale/en-ie.js
js/momentjs/resources/locale/en-nz.js
js/momentjs/resources/locale/eo.js
js/momentjs/resources/locale/es.js
js/momentjs/resources/locale/et.js
js/momentjs/resources/locale/eu.js
js/momentjs/resources/locale/fa.js
js/momentjs/resources/locale/fi.js
js/momentjs/resources/locale/fo.js
js/momentjs/resources/locale/fr-ca.js
js/momentjs/resources/locale/fr-ch.js
js/momentjs/resources/locale/fr.js
js/momentjs/resources/locale/fy.js
js/momentjs/resources/locale/gd.js
