Metadata-Version: 1.0
Name: js.momentjs
Version: 2.13.0
Summary: Fanstatic packaging of Moment.js
Home-page: UNKNOWN
Author: Fanstatic Developers
Author-email: fanstatic@googlegroups.com
License: BSD
Platform: UNKNOWN
